create_flask_skeleton/__init__.py
create_flask_skeleton/template/.flake8
create_flask_skeleton/template/.flaskenv
create_flask_skeleton/template/.gitignore
create_flask_skeleton/template/.pre-commit-config.yaml
create_flask_skeleton/template/LICENSE
create_flask_skeleton/template/Makefile
create_flask_skeleton/template/README.md
create_flask_skeleton/template/app/__init__.py
create_flask_skeleton/template/app/api.py
create_flask_skeleton/template/app/app.py
create_flask_skeleton/template/app/apps/__init__.py
create_flask_skeleton/template/app/apps/admin.py
create_flask_skeleton/template/app/apps/user.py
create_flask_skeleton/template/app/auth.py
create_flask_skeleton/template/app/cors.py
create_flask_skeleton/template/app/db.py
create_flask_skeleton/template/app/globals.py
create_flask_skeleton/template/app/models.py
create_flask_skeleton/template/app/static/index.html
create_flask_skeleton/template/app/templates/hello.html
create_flask_skeleton/template/mypy.ini
create_flask_skeleton/template/pyproject.toml
create_flask_skeleton/template/tests/__init__.py
create_flask_skeleton/template/tests/test_app.py
create_flask_skeleton-0.1.6.dist-info/entry_points.txt
create_flask_skeleton-0.1.6.dist-info/LICENSE
create_flask_skeleton-0.1.6.dist-info/WHEEL
create_flask_skeleton-0.1.6.dist-info/METADATA
create_flask_skeleton-0.1.6.dist-info/RECORD
